{"name":"Logout","id":"logout;logout","testSteps":[{"number":1,"description":"1: Logout ({email\u003djasrivika@gmail.com, password\u003dDoremi@123, result\u003dhomepage})","duration":7711,"startTime":"2022-05-17T17:55:32.283533600+07:00[Asia/Bangkok]","screenshots":[{"screenshot":"4510322e36bb11a6014d8509eafdfeb27c6a3a7394c1f9ef4b696c572e41b18d.png","timeStamp":1652784939994}],"result":"SUCCESS","precondition":false,"level":0,"lineNumber":14,"children":[{"number":2,"description":"Given I am on the login page","duration":3509,"startTime":"2022-05-17T17:55:32.286288500+07:00[Asia/Bangkok]","screenshots":[{"screenshot":"4510322e36bb11a6014d8509eafdfeb27c6a3a7394c1f9ef4b696c572e41b18d.png","timeStamp":1652784935795}],"result":"SUCCESS","precondition":false,"level":1,"children":[{"number":3,"description":"Validate on login page","duration":486,"startTime":"2022-05-17T17:55:35.305159+07:00[Asia/Bangkok]","screenshots":[{"screenshot":"4510322e36bb11a6014d8509eafdfeb27c6a3a7394c1f9ef4b696c572e41b18d.png","timeStamp":1652784935753},{"screenshot":"4510322e36bb11a6014d8509eafdfeb27c6a3a7394c1f9ef4b696c572e41b18d.png","timeStamp":1652784935791}],"result":"SUCCESS","precondition":false,"level":2}]},{"number":4,"description":"And I input \"jasrivika@gmail.com\" email","duration":579,"startTime":"2022-05-17T17:55:35.796899200+07:00[Asia/Bangkok]","screenshots":[{"screenshot":"4510322e36bb11a6014d8509eafdfeb27c6a3a7394c1f9ef4b696c572e41b18d.png","timeStamp":1652784935801},{"screenshot":"b5ff667d1286847405a1c27d0f8afda16770320ea2929e1fe563b01fd35d6693.png","timeStamp":1652784936376}],"result":"SUCCESS","precondition":false,"level":1,"children":[{"number":5,"description":"Input email: jasrivika@gmail.com","duration":568,"startTime":"2022-05-17T17:55:35.802982100+07:00[Asia/Bangkok]","screenshots":[{"screenshot":"4510322e36bb11a6014d8509eafdfeb27c6a3a7394c1f9ef4b696c572e41b18d.png","timeStamp":1652784935932},{"screenshot":"b5ff667d1286847405a1c27d0f8afda16770320ea2929e1fe563b01fd35d6693.png","timeStamp":1652784936371}],"result":"SUCCESS","precondition":false,"level":2}]},{"number":6,"description":"And I input \"Doremi@123\" password","duration":392,"startTime":"2022-05-17T17:55:36.378344900+07:00[Asia/Bangkok]","screenshots":[{"screenshot":"b5ff667d1286847405a1c27d0f8afda16770320ea2929e1fe563b01fd35d6693.png","timeStamp":1652784936382},{"screenshot":"8504198de160ab62f97bfc1ea40b711e1f0031788d5dc01f743d4fb7a659ad9c.png","timeStamp":1652784936771}],"result":"SUCCESS","precondition":false,"level":1,"children":[{"number":7,"description":"Input password: Doremi@123","duration":377,"startTime":"2022-05-17T17:55:36.384331600+07:00[Asia/Bangkok]","screenshots":[{"screenshot":"b5ff667d1286847405a1c27d0f8afda16770320ea2929e1fe563b01fd35d6693.png","timeStamp":1652784936389},{"screenshot":"8504198de160ab62f97bfc1ea40b711e1f0031788d5dc01f743d4fb7a659ad9c.png","timeStamp":1652784936762}],"result":"SUCCESS","precondition":false,"level":2}]},{"number":8,"description":"And I click login button","duration":418,"startTime":"2022-05-17T17:55:36.773289800+07:00[Asia/Bangkok]","screenshots":[{"screenshot":"8504198de160ab62f97bfc1ea40b711e1f0031788d5dc01f743d4fb7a659ad9c.png","timeStamp":1652784936778},{"screenshot":"b37d5f11f457f9ad100e4fbd32e308dd83bd3d7aba878547d2fa89e7b0823305.png","timeStamp":1652784937192}],"result":"SUCCESS","precondition":false,"level":1,"children":[{"number":9,"description":"Click login button","duration":405,"startTime":"2022-05-17T17:55:36.781268900+07:00[Asia/Bangkok]","screenshots":[{"screenshot":"8504198de160ab62f97bfc1ea40b711e1f0031788d5dc01f743d4fb7a659ad9c.png","timeStamp":1652784936791},{"screenshot":"b37d5f11f457f9ad100e4fbd32e308dd83bd3d7aba878547d2fa89e7b0823305.png","timeStamp":1652784937187}],"result":"SUCCESS","precondition":false,"level":2}]},{"number":10,"description":"And I get the \"homepage\"","duration":395,"startTime":"2022-05-17T17:55:37.194165800+07:00[Asia/Bangkok]","screenshots":[{"screenshot":"b37d5f11f457f9ad100e4fbd32e308dd83bd3d7aba878547d2fa89e7b0823305.png","timeStamp":1652784937196},{"screenshot":"498c612155da57717f6749389f3e822a4b9822bae06c089da8fa03936f8fd83b.png","timeStamp":1652784937589}],"result":"SUCCESS","precondition":false,"level":1},{"number":11,"description":"When I click profile icon","duration":1802,"startTime":"2022-05-17T17:55:37.591102700+07:00[Asia/Bangkok]","screenshots":[{"screenshot":"498c612155da57717f6749389f3e822a4b9822bae06c089da8fa03936f8fd83b.png","timeStamp":1652784937594},{"screenshot":"277b24606bfb5bb4d973eeaa48d140aa26bd96409be4808586abd5c0382ca212.png","timeStamp":1652784939393}],"result":"SUCCESS","precondition":false,"level":1,"children":[{"number":12,"description":"Click profile icon","duration":1782,"startTime":"2022-05-17T17:55:37.605067200+07:00[Asia/Bangkok]","screenshots":[{"screenshot":"498c612155da57717f6749389f3e822a4b9822bae06c089da8fa03936f8fd83b.png","timeStamp":1652784937609},{"screenshot":"277b24606bfb5bb4d973eeaa48d140aa26bd96409be4808586abd5c0382ca212.png","timeStamp":1652784939387}],"result":"SUCCESS","precondition":false,"level":2}]},{"number":13,"description":"And I click logout button","duration":427,"startTime":"2022-05-17T17:55:39.395290800+07:00[Asia/Bangkok]","screenshots":[{"screenshot":"277b24606bfb5bb4d973eeaa48d140aa26bd96409be4808586abd5c0382ca212.png","timeStamp":1652784939402},{"screenshot":"4510322e36bb11a6014d8509eafdfeb27c6a3a7394c1f9ef4b696c572e41b18d.png","timeStamp":1652784939823}],"result":"SUCCESS","precondition":false,"level":1,"children":[{"number":14,"description":"Click logout button","duration":412,"startTime":"2022-05-17T17:55:39.405251400+07:00[Asia/Bangkok]","screenshots":[{"screenshot":"277b24606bfb5bb4d973eeaa48d140aa26bd96409be4808586abd5c0382ca212.png","timeStamp":1652784939408},{"screenshot":"4510322e36bb11a6014d8509eafdfeb27c6a3a7394c1f9ef4b696c572e41b18d.png","timeStamp":1652784939818}],"result":"SUCCESS","precondition":false,"level":2}]},{"number":15,"description":"Then I go to login page","duration":166,"startTime":"2022-05-17T17:55:39.824131700+07:00[Asia/Bangkok]","screenshots":[{"screenshot":"4510322e36bb11a6014d8509eafdfeb27c6a3a7394c1f9ef4b696c572e41b18d.png","timeStamp":1652784939827},{"screenshot":"4510322e36bb11a6014d8509eafdfeb27c6a3a7394c1f9ef4b696c572e41b18d.png","timeStamp":1652784939990}],"result":"SUCCESS","precondition":false,"level":1,"children":[{"number":16,"description":"Validate on login page","duration":151,"startTime":"2022-05-17T17:55:39.836101100+07:00[Asia/Bangkok]","screenshots":[{"screenshot":"4510322e36bb11a6014d8509eafdfeb27c6a3a7394c1f9ef4b696c572e41b18d.png","timeStamp":1652784939839},{"screenshot":"4510322e36bb11a6014d8509eafdfeb27c6a3a7394c1f9ef4b696c572e41b18d.png","timeStamp":1652784939987}],"result":"SUCCESS","precondition":false,"level":2}]}]}],"userStory":{"id":"logout","storyName":"Logout","displayName":"Logout","path":"Logout.feature","type":"feature"},"featureTag":{"name":"Logout","type":"feature","displayName":"Logout"},"title":"Logout","description":"","tags":[{"name":"Logout","type":"feature","displayName":"Logout"}],"startTime":"2022-05-17T17:55:32.277312700+07:00[Asia/Bangkok]","duration":8402,"projectKey":"","driver":"chrome","isManualTestingUpToDate":false,"dataTable":{"headers":["email","password","result"],"rows":[{"values":["jasrivika@gmail.com","Doremi@123","homepage"],"lineNumber":14,"result":"SUCCESS"}],"predefinedRows":true,"scenarioOutline":"Given I am on the login page\n\rAnd I input \"\u003cemail\u003e\" email\n\rAnd I input \"\u003cpassword\u003e\" password\n\rAnd I click login button\n\rAnd I get the \"\u003cresult\u003e\"\n\rWhen I click profile icon\n\rAnd I click logout button\n\rThen I go to login page\n\r","dataSetDescriptors":[{"startRow":0,"rowCount":0,"name":"","description":""}]},"manual":false,"testSource":"Cucumber","result":"SUCCESS","scenarioOutline":"Given I am on the login page\r\nAnd I input \"\u003cemail\u003e\" email\r\nAnd I input \"\u003cpassword\u003e\" password\r\nAnd I click login button\r\nAnd I get the \"\u003cresult\u003e\"\r\nWhen I click profile icon\r\nAnd I click logout button\r\nThen I go to login page"}